urlpattern/__init__.py
urlpattern/canonicalize.py
urlpattern/compiler.py
urlpattern/constants.py
urlpattern/construct.py
urlpattern/core.py
urlpattern/match.py
urlpattern/normalizer.py
urlpattern/parser.py
urlpattern/patterns.py
urlpattern/types.py
urlpattern_py-0.2.0.dist-info/licenses/LICENSE
urlpattern_py-0.2.0.dist-info/METADATA
urlpattern_py-0.2.0.dist-info/WHEEL
urlpattern_py-0.2.0.dist-info/top_level.txt
urlpattern_py-0.2.0.dist-info/RECORD
