Metadata-Version: 2.4
Name: urlpattern-py
Version: 0.2.0
Summary: Pure Python implementation of the WHATWG URL Pattern Standard
Author-email: John Karasinski <karasinski@gmail.com>
License: MIT
Project-URL: Homepage, https://github.com/karasinski/urlpattern-py
Project-URL: Bug Tracker, https://github.com/karasinski/urlpattern-py/issues
Classifier: Programming Language :: Python :: 3
Classifier: License :: OSI Approved :: MIT License
Classifier: Operating System :: OS Independent
Classifier: Topic :: Internet :: WWW/HTTP
Classifier: Topic :: Software Development :: Libraries :: Python Modules
Requires-Python: >=3.9
License-File: LICENSE
Provides-Extra: dev
Requires-Dist: pytest; extra == "dev"
Requires-Dist: ruff; extra == "dev"
Requires-Dist: pre-commit; extra == "dev"
Dynamic: license-file
